AUTHORS.rst
CHANGELOG.rst
CONTRIBUTING.rst
LICENSE
MANIFEST.in
README.rst
setup.cfg
setup.py
smart404/__init__.py
smart404/admin.py
smart404/apps.py
smart404/middleware.py
smart404/models.py
smart404.egg-info/PKG-INFO
smart404.egg-info/SOURCES.txt
smart404.egg-info/dependency_links.txt
smart404.egg-info/not-zip-safe
smart404.egg-info/requires.txt
smart404.egg-info/top_level.txt
smart404/migrations/0001_initial.py
smart404/migrations/__init__.py