Metadata-Version: 1.1
Name: smart404
Version: 0.1.1.dev0
Summary: A django module to provide review and redirection of 404 urls from the admin
Home-page: UNKNOWN
Author: Marco Westerhof
Author-email: m.westerhof@lukkien.com
License: MIT
Keywords: smart404
Platform: UNKNOWN
Classifier: Development Status :: 2 - Pre-Alpha
Classifier: Intended Audience :: Developers
Classifier: License :: OSI Approved :: BSD License
Classifier: Natural Language :: English
Classifier: Programming Language :: Python :: 2
Classifier: Programming Language :: Python :: 2.7
Classifier: Programming Language :: Python :: 3
Classifier: Programming Language :: Python :: 3.3
Classifier: Programming Language :: Python :: 3.4
Classifier: Programming Language :: Python :: 3.5
